{
    " ": "",
    "&": "",
    "=": "",
    "A": "      '|\\\u00af\u00af\u00af\\  \u00b0      \n '/\u00af\u00af\u00af/\\     \\        \n |     '|_|    \u00b0|'\u201a   \n |     '|\u00af|    \u00b0|'\u201a   \n |\\___\\_\\___\\\u201a        \n | |     |  |      |  \n\u00b0'\\|___|'\u00b0|__\u00b8\u00b8'|     \n",
    "B": " |\u00af\u00af\u00af|\\\u00af\u00af\u00af\\\u2018        \n |    \u00b0|/___/|      \n |    \u00b0|\\\u00af\u00af\u00af\\|      \n |    \u00b0| |     '|   \n |___|/___/|        \n |     ||     | |   \n |__\u00b8'||__'\u00b8|/\u2018     \n",
    "C": " '/\u00af\u00af\u00af/|\u00af\u00af\u00af|'\u201a      \n |    \u00b0| |___|'\u201a    \n |    \u00b0| |     |'   \n |    \u00b0| |\u00af\u00af\u00af| \u00b0    \n |\\__\u00b8'\\|___| \u00b0     \n | |     ||     |   \n\u00b0'\\|__\u00b8'||__\u00b8'|     \n",
    "D": " |\u00af\u00af\u00af|\\\u00af\u00af\u00af\\\u201a        \n |    \u00b0| |     '|   \n |    \u00b0| |     '|   \n |    \u00b0| |     '|   \n |___|/___/|        \n |     ||     | |   \n |__\u00b8'||__\u00b8'|/\u2018     \n",
    "E": " |\u00af\u00af\u00af\u00af\u00af\u00af\u00af\u00af|         \n |       ____|      \n |       \u00af\u00af\u00af| |     \n |       \u00af\u00af\u00af\u00af|      \n |________|         \n |              |   \n |________|         \n",
    "F": " |\u00af\u00af\u00af\u00af\u00af\u00af\u00af\u00af|         \n |       ____|      \n |       \u00af\u00af| '\u00b0|    \n |      '|\u00af\u00af|\u00b8\u00b8'|   \n |__\u00b8\u00b8\u00b8|__|   \u00b0     \n |      '|'         \n |__\u00b8\u00b8\u00b8|'           \n",
    "G": " '/\u00af\u00af\u00af/|\u00af\u00af\u00af|'\u201a     \n |    \u00b0| |___|'\u201a   \n |    \u00b0| |    \u00b0|'\u201a \n |    \u00b0|'\\\u00af\u00af\u00af\\'\u201a   \n |\\___\\|___|       \n | |     ||     |  \n'\u00b0\\|__\u00b8'||__\u00b8'|    \n",
    "H": " |\\\u00af\u00af\u00af\\ \\\u00af\u00af\u00af\\\u201a         \n | |     |_|     |'    \n'\u00b0\\|            \u00b0|'    \n \u00b0'|     |\u00af|     |'    \n \u00b0|\\___\\\u00b8\\___\\'        \n \u00b0| |     | '|     '|  \n   \\|__\u00b8'| '|__\u00b8\u00b8|     \n",
    "I": " |\\\u00af\u00af\u00af\\\u201a      \n | |     |'   \n\u00b0'\\|     |'   \n '\u00b0|     |'   \n  '|\\__\u00b8'\\'   \n  '| |     |  \n  \u00b0\\|__\u00b8'|    \n",
    "J": " |\u00af\u00af\u00af\u00af\u00af\u00af\u00af\u00af\u00af\u00af\u00af|'           \n |____       ___|'        \n |____|      |__\u00b8|\u2018       \n |\u00af\u00af\u00af'|'|      |          \n |\\__\u00b8'\\|__\u00b8\u00b8'|           \n | |     ||     '|        \n'\u00b0\\|___||___|             \n",
    "K": " |\u00af\u00af\u00af| |\u00af\u00af\u00af|\u201a     \n |    \u00b0|/___/|'   \n |    \u00b0|\\\u00af\u00af\u00af\\|'   \n |___| |     |    \n |     |'/__\u00b8/|   \n |___||   \u00b0| |    \n      \u00b0'|__\u00b8|/'   \n",
    "L": " |\\\u00af\u00af\u00af\\\u2018              \n | |     | '          \n'\u00b0\\|     |___\u00b8'/|     \n '\u00b0|             '|   \n  /________|          \n'\u00b0|              '|   \n'\u00b0|________'|         \n",
    "M": " '/\u00af\u00af\u00af\u00af|  |\u00af\u00af\u00af\u00af\\\u201a            \n |        '\\/         |\u201a     \n |'\\     '|\\   /|     /'|'\u201a  \n | '|   \u00b0'| '\\/ '|    '|\u00b0|'\u201a \n ''/___'\\  | /___'\\/'        \n '|       |'\\|/|       |     \n '|____|  \u00b0|____|            \n",
    "N": " '/\u00af\u00af\u00af\u00af|   /\u00af\u00af\u00af\u00af|           \n |        '\\ '|       /|\u2018   \n |'\\     |\\  \\|      '|''|\u00b0 \n | '|   \u00b0|  \\       \u00b0|/     \n ''/___|\\ /____\u00b8|\u00b0          \n '|      | '\\|        |     \n '|__\u00b8\u00b8'|  '|____''|        \n",
    "O": "         |\\\u00af\u00af\u00af\u00af\\'          \n  /\u00af\u00af\u00af\u00af/\\       \\'\u201a        \n '|       '| '|       |\u2018   \n '|\\       \\/____/|'\u201a      \n '| '\\____\\      | |       \n  \\ '|       |___'|/\u2018      \n   '\\|____|     \u00b0          \n",
    "P": "  |\u00af\u00af\u00af\u00af|\\\u00af\u00af\u00af\u00af\\\u2018         \n  |       | |       | \u00b0 \n  |       |/____/|      \n  |       |      \u00b0| |   \n  |____|____'|/'        \n  |       |       \u2018     \n  |____|\u2018               \n",
    "Q": "         |\\\u00af\u00af\u00af\u00af\\          \n  /\u00af\u00af\u00af\u00af/\\       \\\u201a        \n '|       '| '|       |\u00b0  \n '|\\       \\/\\\u00af\u00af'''\\/|\u2018   \n '| '\\____\\'|___|\u2018        \n  \\ '|      \u00b0||     |     \n   '\\|___\u00b8\u00b8||___|\u2018        \n",
    "R": "  |\u00af\u00af\u00af\u00af|\\\u00af\u00af\u00af\u00af\u2018\\      \n  |       |/____/|   \n  |       |\\\u00af\u00af\u00af\u00af\\|   \n  |____| |       |\u00b0  \n  |       |/____/|   \n  |____||     \u00b0| | \u00b0 \n          '|___\u00b8|/   \n",
    "S": "  /\u00af\u00af\u00af\u00af/|\u00af\u00af\u00af\u00af|          \n  \\____\\|____|          \n  |\u00af\u00af\u00af\u00af|\\\u00af\u00af\u00af\u00af\\          \n  |       | |       |'  \n  |\\___\u00b8'\\|___\u00b8/|\u00b0      \n  | |      '||    \u00b0| |\u00b0 \n \u00b0'\\|___\u00b8||__\u00b8\u00b8|/       \n",
    "T": "  |\u00af\u00af\u00af\u00af\u00af\u00af\u00af\u00af\u00af\u00af|           \n  |___       ___|        \n  |     |      |     |   \n  |___|    \u00b0'|___|\u2018      \n        |___'|\u2018          \n        |      |'        \n        |__\u00b8\u00b8'|'         \n",
    "U": "  |\\\u00af\u00af\u00af\\  |\\\u00af\u00af\u00af\\ \u00b0        \n  | |     '|\u00b0| |     '|'  \n \u00b0'/     '/  '/     /|\u2018   \n  |       \\'/      | |'   \n  |\\_____/|__\u00b8\\'          \n  | |       '| |     |    \n \u00b0'\\|____'|/|___|\u2018        \n",
    "V": "  |\\\u00af\u00af\u00af\\   '/\u00af\u00af\u00af/|        \n  | '\\     \\ /     / '|   \n  '\\  \\     '     /  /'   \n    \\  \\       '/  /      \n      \\ '\\_\u00b8_/  /'        \n       '\\ |   '| /        \n         '|__|''          \n",
    "W": "  |\\\u00af\u00af\u00af\\    '/\u00af\u00af\u00af/|        \n  | '\\     \\/\\/     / '|   \n   \\  \\           /  /'    \n    '\\  \\   '.   '/  /     \n      \\  \\\u00b8/||\\\u00b8/  /       \n       '\\ || || || /'      \n         '||/ '\\||'        \n",
    "X": "  |\u00af\u00af\u00af|   |\u00af\u00af\u00af|        \n  |\\     \\ /     /|    \n  |' \u00b7     \u00b7     \u00b7'|   \n  '/     / \\     \\' '  \n  |___|   |___|        \n  |     |  \u00b0|     |\u00b0   \n  |___|   |___|        \n",
    "Y": "  |\u00af\u00af\u00af|   |\u00af\u00af\u00af|\u00b0      \n  |\\     \\\u00b0 |     |\u00b0  \n  |  \\__\u00b8\\'|     |'   \n \u00b0'|\u00af\u00af\u00af|  |     |\u2018    \n   |\\___\\|___|        \n   | |     ||     |   \n  \u00b0'\\|__\u00b8'||__\u00b8'|     \n",
    "Z": "  |\\\u00af\u00af\u00af\u00af\u00af\u00af\u00af\u00af\u00af/|\u2018         \n  | '\\___       /  |\u2018    \n   \\ | '  /     '/   /\u00b0  \n    ''|_'/        \u00af\u00af/|\u2018  \n      /_______/\u00b0|\u2018       \n     |             | '/  \n     |______\u00b8'''|/'      \n",
    "a": "      '|\\\u00af\u00af\u00af\\  \u00b0      \n '/\u00af\u00af\u00af/\\     \\        \n |     '|_|    \u00b0|'\u201a   \n |     '|\u00af|    \u00b0|'\u201a   \n |\\___\\_\\___\\\u201a        \n | |     |  |      |  \n\u00b0'\\|___|'\u00b0|__\u00b8\u00b8'|     \n",
    "b": " |\u00af\u00af\u00af|\\\u00af\u00af\u00af\\\u2018        \n |    \u00b0|/___/|      \n |    \u00b0|\\\u00af\u00af\u00af\\|      \n |    \u00b0| |     '|   \n |___|/___/|        \n |     ||     | |   \n |__\u00b8'||__'\u00b8|/\u2018     \n",
    "c": " '/\u00af\u00af\u00af/|\u00af\u00af\u00af|'\u201a      \n |    \u00b0| |___|'\u201a    \n |    \u00b0| |     |'   \n |    \u00b0| |\u00af\u00af\u00af| \u00b0    \n |\\__\u00b8'\\|___| \u00b0     \n | |     ||     |   \n\u00b0'\\|__\u00b8'||__\u00b8'|     \n",
    "d": " |\u00af\u00af\u00af|\\\u00af\u00af\u00af\\\u201a        \n |    \u00b0| |     '|   \n |    \u00b0| |     '|   \n |    \u00b0| |     '|   \n |___|/___/|        \n |     ||     | |   \n |__\u00b8'||__\u00b8'|/\u2018     \n",
    "e": " |\u00af\u00af\u00af\u00af\u00af\u00af\u00af\u00af|         \n |       ____|      \n |       \u00af\u00af\u00af| |     \n |       \u00af\u00af\u00af\u00af|      \n |________|         \n |              |   \n |________|         \n",
    "f": " |\u00af\u00af\u00af\u00af\u00af\u00af\u00af\u00af|         \n |       ____|      \n |       \u00af\u00af| '\u00b0|    \n |      '|\u00af\u00af|\u00b8\u00b8'|   \n |__\u00b8\u00b8\u00b8|__|   \u00b0     \n |      '|'         \n |__\u00b8\u00b8\u00b8|'           \n",
    "g": " '/\u00af\u00af\u00af/|\u00af\u00af\u00af|'\u201a     \n |    \u00b0| |___|'\u201a   \n |    \u00b0| |    \u00b0|'\u201a \n |    \u00b0|'\\\u00af\u00af\u00af\\'\u201a   \n |\\___\\|___|       \n | |     ||     |  \n'\u00b0\\|__\u00b8'||__\u00b8'|    \n",
    "h": " |\\\u00af\u00af\u00af\\ \\\u00af\u00af\u00af\\\u201a         \n | |     |_|     |'    \n'\u00b0\\|            \u00b0|'    \n \u00b0'|     |\u00af|     |'    \n \u00b0|\\___\\\u00b8\\___\\'        \n \u00b0| |     | '|     '|  \n   \\|__\u00b8'| '|__\u00b8\u00b8|     \n",
    "i": " |\\\u00af\u00af\u00af\\\u201a      \n | |     |'   \n\u00b0'\\|     |'   \n '\u00b0|     |'   \n  '|\\__\u00b8'\\'   \n  '| |     |  \n  \u00b0\\|__\u00b8'|    \n",
    "j": " |\u00af\u00af\u00af\u00af\u00af\u00af\u00af\u00af\u00af\u00af\u00af|'           \n |____       ___|'        \n |____|      |__\u00b8|\u2018       \n |\u00af\u00af\u00af'|'|      |          \n |\\__\u00b8'\\|__\u00b8\u00b8'|           \n | |     ||     '|        \n'\u00b0\\|___||___|             \n",
    "k": " |\u00af\u00af\u00af| |\u00af\u00af\u00af|\u201a     \n |    \u00b0|/___/|'   \n |    \u00b0|\\\u00af\u00af\u00af\\|'   \n |___| |     |    \n |     |'/__\u00b8/|   \n |___||   \u00b0| |    \n      \u00b0'|__\u00b8|/'   \n",
    "l": " |\\\u00af\u00af\u00af\\\u2018              \n | |     | '          \n'\u00b0\\|     |___\u00b8'/|     \n '\u00b0|             '|   \n  /________|          \n'\u00b0|              '|   \n'\u00b0|________'|         \n",
    "m": " '/\u00af\u00af\u00af\u00af|  |\u00af\u00af\u00af\u00af\\\u201a            \n |        '\\/         |\u201a     \n |'\\     '|\\   /|     /'|'\u201a  \n | '|   \u00b0'| '\\/ '|    '|\u00b0|'\u201a \n ''/___'\\  | /___'\\/'        \n '|       |'\\|/|       |     \n '|____|  \u00b0|____|            \n",
    "n": " '/\u00af\u00af\u00af\u00af|   /\u00af\u00af\u00af\u00af|           \n |        '\\ '|       /|\u2018   \n |'\\     |\\  \\|      '|''|\u00b0 \n | '|   \u00b0|  \\       \u00b0|/     \n ''/___|\\ /____\u00b8|\u00b0          \n '|      | '\\|        |     \n '|__\u00b8\u00b8'|  '|____''|        \n",
    "o": "         |\\\u00af\u00af\u00af\u00af\\'          \n  /\u00af\u00af\u00af\u00af/\\       \\'\u201a        \n '|       '| '|       |\u2018   \n '|\\       \\/____/|'\u201a      \n '| '\\____\\      | |       \n  \\ '|       |___'|/\u2018      \n   '\\|____|     \u00b0          \n",
    "p": "  |\u00af\u00af\u00af\u00af|\\\u00af\u00af\u00af\u00af\\\u2018         \n  |       | |       | \u00b0 \n  |       |/____/|      \n  |       |      \u00b0| |   \n  |____|____'|/'        \n  |       |       \u2018     \n  |____|\u2018               \n",
    "q": "         |\\\u00af\u00af\u00af\u00af\\          \n  /\u00af\u00af\u00af\u00af/\\       \\\u201a        \n '|       '| '|       |\u00b0  \n '|\\       \\/\\\u00af\u00af'''\\/|\u2018   \n '| '\\____\\'|___|\u2018        \n  \\ '|      \u00b0||     |     \n   '\\|___\u00b8\u00b8||___|\u2018        \n",
    "r": "  |\u00af\u00af\u00af\u00af|\\\u00af\u00af\u00af\u00af\u2018\\      \n  |       |/____/|   \n  |       |\\\u00af\u00af\u00af\u00af\\|   \n  |____| |       |\u00b0  \n  |       |/____/|   \n  |____||     \u00b0| | \u00b0 \n          '|___\u00b8|/   \n",
    "s": "  /\u00af\u00af\u00af\u00af/|\u00af\u00af\u00af\u00af|          \n  \\____\\|____|          \n  |\u00af\u00af\u00af\u00af|\\\u00af\u00af\u00af\u00af\\          \n  |       | |       |'  \n  |\\___\u00b8'\\|___\u00b8/|\u00b0      \n  | |      '||    \u00b0| |\u00b0 \n \u00b0'\\|___\u00b8||__\u00b8\u00b8|/       \n",
    "t": "  |\u00af\u00af\u00af\u00af\u00af\u00af\u00af\u00af\u00af\u00af|           \n  |___       ___|        \n  |     |      |     |   \n  |___|    \u00b0'|___|\u2018      \n        |___'|\u2018          \n        |      |'        \n        |__\u00b8\u00b8'|'         \n",
    "u": "  |\\\u00af\u00af\u00af\\  |\\\u00af\u00af\u00af\\ \u00b0        \n  | |     '|\u00b0| |     '|'  \n \u00b0'/     '/  '/     /|\u2018   \n  |       \\'/      | |'   \n  |\\_____/|__\u00b8\\'          \n  | |       '| |     |    \n \u00b0'\\|____'|/|___|\u2018        \n",
    "v": "  |\\\u00af\u00af\u00af\\   '/\u00af\u00af\u00af/|        \n  | '\\     \\ /     / '|   \n  '\\  \\     '     /  /'   \n    \\  \\       '/  /      \n      \\ '\\_\u00b8_/  /'        \n       '\\ |   '| /        \n         '|__|''          \n",
    "w": "  |\\\u00af\u00af\u00af\\    '/\u00af\u00af\u00af/|        \n  | '\\     \\/\\/     / '|   \n   \\  \\           /  /'    \n    '\\  \\   '.   '/  /     \n      \\  \\\u00b8/||\\\u00b8/  /       \n       '\\ || || || /'      \n         '||/ '\\||'        \n",
    "x": "  |\u00af\u00af\u00af|   |\u00af\u00af\u00af|        \n  |\\     \\ /     /|    \n  |' \u00b7     \u00b7     \u00b7'|   \n  '/     / \\     \\' '  \n  |___|   |___|        \n  |     |  \u00b0|     |\u00b0   \n  |___|   |___|        \n",
    "y": "  |\u00af\u00af\u00af|   |\u00af\u00af\u00af|\u00b0      \n  |\\     \\\u00b0 |     |\u00b0  \n  |  \\__\u00b8\\'|     |'   \n \u00b0'|\u00af\u00af\u00af|  |     |\u2018    \n   |\\___\\|___|        \n   | |     ||     |   \n  \u00b0'\\|__\u00b8'||__\u00b8'|     \n",
    "z": "  |\\\u00af\u00af\u00af\u00af\u00af\u00af\u00af\u00af\u00af/|\u2018         \n  | '\\___       /  |\u2018    \n   \\ | '  /     '/   /\u00b0  \n    ''|_'/        \u00af\u00af/|\u2018  \n      /_______/\u00b0|\u2018       \n     |             | '/  \n     |______\u00b8'''|/'      \n"
}