{
    " ": "   \n   \n   \n   \n   \n   \n   \n",
    "!": "  __  \n  LJ  \n  FJ  \n J__L \n  __  \n J__L \n |__| \n      \n",
    "\"": "  _  _  \n EJ  LJ \n --  -- \n        \n        \n        \n        \n        \n",
    "#": "     _  _     \n   _FJ__L]_   \n  |   __   |  \n  _| |__| |_  \n L_   __   _J \n LJ__F__J__LJ \n  |__L  J__|  \n              \n",
    "$": "    _F]_   \n   F ___L  \n  J (___|  \n  J\\___ \\  \n .--___) \\ \n J\\__  __J \n  J__LJ__F \n     LJ    \n",
    "&": "",
    "'": " __ \n FJ \n L- \n -  \n    \n    \n    \n    \n",
    "(": "    _   \n  .'_|  \n / /-'  \n | L    \n \\ \\__  \n \\'.__L \n  '.__| \n        \n",
    ")": "   _    \n  |_'.  \n  '-\\ \\ \n    J | \n  __/ / \n J__.'/ \n |__.'  \n        \n",
    "*": "     __     \n   /\\FJ/\\   \n   \\    /   \n  .'    '.  \n J\\.n  n./L \n  \\/J__L\\/  \n    |__|    \n            \n",
    "+": "          \n    __    \n  __FJ__  \n |__  __| \n L_J__L_J \n   J__L   \n          \n          \n",
    ",": "        \n        \n        \n        \n    __  \n   J  L \n   |_F  \n   |_F  \n",
    "-": "          \n          \n  ______  \n |______| \n L______J \n          \n          \n          \n",
    ".": "      \n      \n      \n      \n  __  \n J__L \n |__| \n      \n",
    "/": "       _ \n      // \n     / F \n    / /' \n   /  F  \n  /__/F  \n J___|   \n         \n",
    "0": "    ____    \n   F _  ]   \n  J |/ | L  \n  | | /| |  \n  F  /_J J  \n J\\______/F \n  J______F  \n            \n",
    "1": "  __  \n / J  \n LFJ  \n J  L \n J  L \n J__L \n |__| \n      \n",
    "2": "    ____    \n   / _  `.  \n  J_/-7 .'  \n  `-:'.'.'  \n  .' ;_J__  \n J________L \n |________| \n            \n",
    "3": "    ____    \n   F___ J   \n   `-__| L  \n    |__  (  \n .-____] J  \n J\\______/F \n  J______F  \n            \n",
    "4": "   _  _    \n  FJ  L]   \n J |__| L  \n |____  |  \n L____J J  \n      J__L \n      J__| \n           \n",
    "5": "    ____   \n   F ___L  \n  J |___|  \n  |____ \\  \n .--___) \\ \n J\\______J \n  J______F \n           \n",
    "6": "    ____    \n   F ___]   \n  J `--_]   \n  | ,--. L  \n  F L__J |  \n J\\______/L \n  J______F  \n            \n",
    "7": "  ____  \n F___ ] \n `--7 / \n   / // \n  J  L  \n  J__L  \n  |__|  \n        \n",
    "8": "    ____    \n   F __ J   \n  J `--' L  \n  / ,--. \\  \n  F L__J J  \n J\\______/L \n  J______F  \n            \n",
    "9": "   ____    \n  F __ J   \n J '--' L  \n J`---. |  \n  `---J J  \n      J__L \n      J__| \n           \n",
    ":": "      \n  __  \n  LJ  \n  --  \n  __  \n J__L \n |__| \n      \n",
    ";": "      \n  __  \n  LJ  \n  --  \n  __  \n J  L \n |_F  \n |_F  \n",
    "<": "       _   \n   _-\"\"_L  \n ,\" .\"\"-'  \n |\"-_\"--_  \n  \"-_\"--_L \n     \"--_| \n           \n           \n",
    "=": "",
    ">": "    _       \n   J_\"\"-_   \n   `-\"\". \", \n  __--\"_-\"| \n J_--\"\"_-\"  \n  |_--\"     \n            \n            \n",
    "?": "   ____   \n ,\"__  \". \n FJ--/ J| \n -- /_//  \n   J__/   \n   J__L   \n   |__|   \n          \n",
    "@": "    ____    \n   F __ ]   \n  J |  | L  \n  | |[L' |  \n  F L_-_/_  \n J\\______/L \n  J______F  \n            \n",
    "A": "      _      \n     /.\\     \n    //_\\\\    \n   / ___ \\   \n  / L___J \\  \n J__L   J__L \n |__L   J__| \n             \n",
    "B": "    ___    \n   F _ \",  \n  J `-'(|  \n  | ,--.\\  \n  F L__J \\ \n J_______J \n |_______F \n           \n",
    "C": "    ___    \n  ,\"___\".  \n  FJ---L]  \n J |   LJ  \n | \\___--. \n J\\_____/F \n  J_____F  \n           \n",
    "D": "    ___    \n   F __\".  \n  J |--\\ L \n  | |  J | \n  F L__J | \n J______/F \n |______F  \n           \n",
    "E": "    ____    \n   F ___J   \n  J |___:   \n  | _____|  \n  F L____:  \n J________L \n |________| \n            \n",
    "F": "    ____   \n   F ___J  \n  J |___:  \n  | _____| \n  F |____J \n J__F      \n |__|      \n           \n",
    "G": "    ___    \n  ,\"___\".  \n  FJ---L]  \n J |  [\"\"L \n | \\___] | \n J\\_____/F \n  J_____F  \n           \n",
    "H": "    _  _    \n   FJ  L]   \n  J |__| L  \n  |  __  |  \n  F L__J J  \n J__L  J__L \n |__L  J__| \n            \n",
    "I": "   __   \n   FJ   \n  J  L  \n  |  |  \n  F  J  \n J____L \n |____| \n        \n",
    "J": "     _   \n     L]  \n     | L \n     | | \n.--__J J \nJ\\_____/ \n J_____/ \n         \n",
    "K": "   _  _    \n  FJ / ;   \n J |/ (|   \n |     L   \n F L:\\  L  \nJ__L \\\\__L \n|__L  \\L_| \n           \n",
    "L": "    _       \n   FJ       \n  J |       \n  | |       \n  F L_____  \n J________L \n |________| \n            \n",
    "M": "    __  __    \n   F  \\/  ]   \n  J |\\__/| L  \n  | |`--'| |  \n  F L    J J  \n J__L    J__L \n |__L    J__| \n              \n",
    "N": "    _  _    \n   F L L]   \n  J   \\| L  \n  | |\\   |  \n  F L\\\\  J  \n J__L \\\\__L \n |__L  J__| \n            \n",
    "O": "    ____    \n   F __ ]   \n  J |--| L  \n  | |  | |  \n  F L__J J  \n J\\______/F \n  J______F  \n            \n",
    "P": "    ___   \n   F _ \", \n  J `-' | \n  |  __/F \n  F |__/  \n J__|     \n |__L     \n          \n",
    "Q": "    ____    \n   F __ ]   \n  J |--| L  \n  | | _| |  \n  F L_F  J  \n J\\_____  \\ \n  J_____\\J] \n        \\J  \n",
    "R": "    ___     \n   F _ \",   \n  J `-'(|   \n  |  _  L   \n  F |_\\  L  \n J__| \\\\__L \n |__|  J__| \n            \n",
    "S": "    ___    \n   F __\".  \n  J (___|  \n  J\\___ \\  \n .--___) \\ \n J\\______J \n  J______F \n           \n",
    "T": "  ____  \n /_  _\\ \n [J  L] \n  |  |  \n  F  J  \n J____L \n |____| \n        \n",
    "U": "    _  _    \n   FJ  L]   \n  J |  | L  \n  | |  | |  \n  F L__J J  \n J\\______/F \n  J______F  \n            \n",
    "V": "   _  _   \n  FJ  L]  \n J |  | L \n J J  F L \n J\\ \\/ /F \n  \\\\__//  \n   \\__/   \n          \n",
    "W": "    _    _    \n   F L  J J   \n  J J .. L L  \n  | |/  \\| |  \n  F   /\\   J  \n J___//\\\\___L \n |___/  \\___| \n              \n",
    "X": "    _  _    \n   FJ  LJ   \n   J \\/ F   \n   /    \\   \n  /  /\\  \\  \n J__//\\\\__L \n |__/  \\__| \n            \n",
    "Y": "  _  _  \n FJ  LJ \n J \\/ F \n J\\  /L \n  F  J  \n |____| \n |____| \n        \n",
    "Z": "    ____    \n   [__  '.  \n   `--7 .'  \n    .'.'.'  \n  .' (_(__  \n J________L \n |________| \n            \n",
    "[": "    ____    \n   F ___J   \n  J |---'   \n  | |       \n  F L_____  \n J________L \n |________| \n            \n",
    "\\": " _       \n \\\\      \n J \\     \n '\\ \\    \n  J  \\   \n  J\\__\\  \n   |___L \n         \n",
    "]": "    ____    \n   L___ ]   \n   `---| L  \n       | |  \n  _____J J  \n J________L \n |________| \n            \n",
    "^": "   /\\   \n  /  \\  \n /_/\\_\\ \n L_/\\_J \n        \n        \n        \n        \n",
    "_": "            \n            \n            \n            \n            \n  ________  \n |________| \n L________J \n",
    "`": " _   \n \\\\  \n \\\\\\ \n     \n     \n     \n     \n     \n",
    "a": "            \n    ___ _   \n   F __` L  \n  | |--| |  \n  F L__J J  \n J\\____,__L \n  J____,__F \n            \n",
    "b": "    _       \n   FJ___    \n  J  __ J   \n  | |--| |  \n  F L__J J  \n J__,____/L \n J__,____F  \n            \n",
    "c": "            \n    ____    \n   F ___J.  \n  | |---LJ  \n  F L___--. \n J\\______/F \n  J______F  \n            \n",
    "d": "       _    \n    ___FJ   \n   F __  L  \n  | |--| |  \n  F L__J J  \n J\\____,__L \n  J____,__F \n            \n",
    "e": "            \n    ____    \n   F __ J   \n  | _____J  \n  F L___--. \n J\\______/F \n  J______F  \n            \n",
    "f": "    ____  \n   / ___J \n  J |_--' \n  |  _|   \n  F |_J   \n J__F     \n |__|     \n          \n",
    "g": "            \n    ___ _   \n   F __` L  \n  | |--| |  \n  F L__J J  \n  )-____  L \n J\\______/F \n  J______F  \n",
    "h": "    _       \n   FJ___    \n  J  __ `.  \n  | |--| |  \n  F L  J J  \n J__L  J__L \n |__L  J__| \n            \n",
    "i": "  __  \n  LJ  \n      \n  FJ  \n J  L \n J__L \n |__| \n      \n",
    "j": "    __   \n    LJ   \n     _   \n    J J  \n    J  L \n ,-_J  | \n \\_____/ \n \\_____/ \n",
    "k": "   _       \n  FJ __    \n J |/ /L   \n |    \\    \n F L:\\ J   \nJ__L \\\\_J. \n|__L  \\L_| \n           \n",
    "l": "  __  \n  LJ  \n  FJ  \n J  L \n J  L \n J__L \n |__| \n      \n",
    "m": "              \n   _ _____    \n  J '_  _ `,  \n  | |_||_| |  \n  F L LJ J J  \n J__L LJ J__L \n |__L LJ J__| \n              \n",
    "n": "            \n   _ ___    \n  J '__ J   \n  | |__| |  \n  F L  J J  \n J__L  J__L \n |__L  J__| \n            \n",
    "o": "            \n    ____    \n   F __ J   \n  | |--| |  \n  F L__J J  \n J\\______/F \n  J______F  \n            \n",
    "p": "            \n   _ ___    \n  J '__ J   \n  | |--| |  \n  F L__J J  \n J  _____/L \n |_J_____F  \n L_J        \n",
    "q": "            \n    ___ _   \n   F __` L  \n  | |--| |  \n  F L__J J  \n J\\_____  L \n  J_____L_| \n        L_J \n",
    "r": "           \n   _ ___   \n  J '__ \", \n  | |__|-J \n  F L  `-' \n J__L      \n |__L      \n           \n",
    "s": "            \n    ____    \n   F ___J   \n  | '----_  \n  )-____  L \n J\\______/F \n  J______F  \n            \n",
    "t": "   _     \n  FJ_    \n J  _|   \n | |-'   \n F |__-. \n \\_____/ \n J_____F \n         \n",
    "u": "            \n   _    _   \n  J |  | L  \n  | |  | |  \n  F L__J J  \n J\\____,__L \n  J____,__F \n            \n",
    "v": "          \n  _    _  \n J |  | L \n J J  F L \n J\\ \\/ /F \n  \\\\__//  \n   \\__/   \n          \n",
    "w": "              \n    _    _    \n   FJ .. L]   \n  | |/  \\| |  \n  F   /\\   J  \n J\\__//\\\\__/L \n  \\__/  \\__/  \n              \n",
    "x": "           \n   _   _   \n  J \\ / F  \n   \\ ' /   \n  .' . `.  \n J__/:\\__L \n |__/ \\__| \n           \n",
    "y": "            \n   _    _   \n  J |  | L  \n  | |  | |  \n  F L__J J  \n  )-____  L \n J\\______/F \n  J______F  \n",
    "z": "           \n   _____   \n  [__   F  \n  `-.'.'/  \n  .' (_(_  \n J_______L \n |_______| \n           \n",
    "{": "      _    \n    .\"_J   \n  _/ /-'   \n |_ (/     \n L_L.\"-__  \n   \"_\"-__L \n     \"-__| \n           \n",
    "|": "  []  \n  LJ  \n  FJ  \n J  L \n J  L \n J  L \n |__| \n |__| \n",
    "}": "    _      \n   F_\".    \n   '-\\ \\_  \n     \\) _| \n  __-\".J_J \n J__-\"_\"   \n |__-\"     \n           \n",
    "~": "       \n  /\\/] \n /   / \n L/\\// \n L/\\/  \n       \n       \n       \n"
}