{
    " ": "   \n   \n   \n   \n   \n   \n   \n",
    "!": " _  \n( ) \n| | \n| | \n| | \n(_) \n(_) \n    \n",
    "\"": "  _  _   \n ( )( )  \n (_)(_)  \n         \n         \n         \n         \n         \n",
    "#": "           \n   _  _    \n _( )( )_  \n(_  ..  _) \n(_      _) \n  (_)(_)   \n           \n           \n",
    "$": "  ( )   \n /'_ \\  \n( (_(_) \n \\__ \\  \n( )_) ) \n`\\_ _/' \n  (_)   \n        \n",
    "&": "",
    "'": " _  \n( ) \n|/  \n    \n    \n    \n    \n    \n",
    "(": "   _  \n /' ) \n| ,/' \n| |   \n| `\\  \n`\\__) \n      \n      \n",
    ")": " _    \n( `\\  \n`\\  | \n  | | \n /' | \n(__/' \n      \n      \n",
    "*": "   _    \n _( )_  \n( ` ' ) \n >   <  \n(_, ,_) \n  (_)   \n        \n        \n",
    "+": "    _     \n   ( )    \n __| |__  \n(__   __) \n   | |    \n   (_)    \n          \n          \n",
    ",": "    \n    \n    \n    \n _  \n( ) \n|/  \n    \n",
    "-": "         \n         \n ______  \n(______) \n         \n         \n         \n         \n",
    ".": "    \n    \n    \n    \n _  \n(_) \n    \n    \n",
    "/": "        __  \n       /  ) \n     /' /'  \n   /' /'    \n /' /'      \n(_/'        \n            \n            \n",
    "0": "  __    \n/' _`\\  \n| ( ) | \n| | | | \n| (_) | \n`\\___/' \n        \n        \n",
    "1": "   _  \n /' ) \n(_, | \n  | | \n  | | \n  (_) \n      \n      \n",
    "2": "   __    \n /'__`\\  \n(_)  ) ) \n   /' /  \n /' /( ) \n(_____/' \n         \n         \n",
    "3": "   ___  \n /'_  ) \n(_)_) | \n _(_ <  \n( )_) | \n`\\____) \n        \n        \n",
    "4": " _  _    \n( )( )   \n| || |   \n| || |_  \n(__ ,__) \n   (_)   \n         \n         \n",
    "5": " _____  \n(  ___) \n| (__   \n|___ `\\ \n( )_) | \n`\\___/' \n        \n        \n",
    "6": " _____  \n(  ___) \n| (__   \n|  _ `\\ \n| (_) | \n`\\___/' \n        \n        \n",
    "7": " _______  \n(_____  ) \n     /'/' \n   /'/'   \n /'/'     \n(_/       \n          \n          \n",
    "8": "   _    \n /'_`\\  \n( (_) ) \n > _ <' \n( (_) ) \n`\\___/' \n        \n        \n",
    "9": "   __   \n /'_ `\\ \n( (_) | \n \\__, | \n    | | \n    (_) \n        \n        \n",
    ":": "    \n    \n _  \n(_) \n _  \n(_) \n    \n    \n",
    ";": "    \n    \n _  \n(_) \n _  \n( ) \n|/  \n    \n",
    "<": "     _  \n   /' ) \n /' /'  \n<  <    \n \\  `\\  \n  `\\__) \n        \n        \n",
    "=": "",
    ">": " _      \n( `\\    \n `\\ `\\  \n   >  > \n /' /'  \n(_/'    \n        \n        \n",
    "?": "   _    \n /'_`\\  \n(_) ) | \n   /'/' \n  |_|   \n  (_)   \n        \n        \n",
    "@": "           \n     _     \n   /'_`\\   \n /'/'_` )  \n( ( (_| |  \n \\ `\\__,_) \n  `\\_____) \n           \n",
    "A": " _____  \n(  _  ) \n| (_) | \n|  _  | \n| | | | \n(_) (_) \n        \n        \n",
    "B": " ___    \n(  _`\\  \n| (_) ) \n|  _ <' \n| (_) ) \n(____/' \n        \n        \n",
    "C": " ___    \n(  _`\\  \n| ( (_) \n| |  _  \n| (_( ) \n(____/' \n        \n        \n",
    "D": " ___    \n(  _`\\  \n| | ) | \n| | | ) \n| |_) | \n(____/' \n        \n        \n",
    "E": " ___    \n(  _`\\  \n| (_(_) \n|  _)_  \n| (_( ) \n(____/' \n        \n        \n",
    "F": " ___    \n(  _`\\  \n| (_(_) \n|  _)   \n| |     \n(_)     \n        \n        \n",
    "G": " ___    \n(  _`\\  \n| ( (_) \n| |___  \n| (_, ) \n(____/' \n        \n        \n",
    "H": " _   _  \n( ) ( ) \n| |_| | \n|  _  | \n| | | | \n(_) (_) \n        \n        \n",
    "I": " _  \n(_) \n| | \n| | \n| | \n(_) \n    \n    \n",
    "J": " _____  \n(___  ) \n    | | \n _  | | \n( )_| | \n`\\___/' \n        \n        \n",
    "K": " _   _  \n( ) ( ) \n| |/'/' \n| , <   \n| |\\`\\  \n(_) (_) \n        \n        \n",
    "L": " _      \n( )     \n| |     \n| |  _  \n| |_( ) \n(____/' \n        \n        \n",
    "M": "        \n/'\\_/`\\ \n|     | \n| (_) | \n| | | | \n(_) (_) \n        \n        \n",
    "N": " _   _  \n( ) ( ) \n| `\\| | \n| , ` | \n| |`\\ | \n(_) (_) \n        \n        \n",
    "O": " _____  \n(  _  ) \n| ( ) | \n| | | | \n| (_) | \n(_____) \n        \n        \n",
    "P": " ___    \n(  _`\\  \n| |_) ) \n| ,__/' \n| |     \n(_)     \n        \n        \n",
    "Q": " _____  \n(  _  ) \n| ( ) | \n| | | | \n| (('\\| \n(___\\_) \n        \n        \n",
    "R": " ___    \n|  _`\\  \n| (_) ) \n| ,  /  \n| |\\ \\  \n(_) (_) \n        \n        \n",
    "S": " ___    \n(  _`\\  \n| (_(_) \n`\\__ \\  \n( )_) | \n`\\____) \n        \n        \n",
    "T": " _____  \n(_   _) \n  | |   \n  | |   \n  | |   \n  (_)   \n        \n        \n",
    "U": " _   _  \n( ) ( ) \n| | | | \n| | | | \n| (_) | \n(_____) \n        \n        \n",
    "V": " _   _  \n( ) ( ) \n| | | | \n| | | | \n| \\_/ | \n`\\___/' \n        \n        \n",
    "W": " _       _  \n( )  _  ( ) \n| | ( ) | | \n| | | | | | \n| (_/ \\_) | \n`\\___x___/' \n            \n            \n",
    "X": " _    _  \n( )  ( ) \n`\\`\\/'/' \n  >  <   \n /'/\\`\\  \n(_)  (_) \n         \n         \n",
    "Y": " _     _  \n( )   ( ) \n`\\`\\_/'/' \n  `\\ /'   \n   | |    \n   (_)    \n          \n          \n",
    "Z": " _______  \n(_____  ) \n     /'/' \n   /'/'   \n /'/'___  \n(_______) \n          \n          \n",
    "[": " ___  \n(  _) \n| |   \n| |   \n| |_  \n(___) \n      \n      \n",
    "\\": " _          \n( `\\        \n `\\ `\\      \n   `\\ `\\    \n     `\\ `\\  \n       `\\_) \n            \n            \n",
    "]": " ___  \n(_  ) \n  | | \n  | | \n _| | \n(___) \n      \n      \n",
    "^": "  __   \n /  \\  \n(_/\\_) \n       \n       \n       \n       \n       \n",
    "_": "         \n         \n         \n         \n         \n         \n ______  \n(______) \n",
    "`": " _  \n( ) \n \\| \n    \n    \n    \n    \n    \n",
    "a": "        \n        \n   _ _  \n /'_` ) \n( (_| | \n`\\__,_) \n        \n        \n",
    "b": " _      \n( )     \n| |_    \n| '_`\\  \n| |_) ) \n(_,__/' \n        \n        \n",
    "c": "        \n        \n   ___  \n /'___) \n( (___  \n`\\____) \n        \n        \n",
    "d": "     _  \n    ( ) \n   _| | \n /'_` | \n( (_| | \n`\\__,_) \n        \n        \n",
    "e": "        \n        \n   __   \n /'__`\\ \n(  ___/ \n`\\____) \n        \n        \n",
    "f": "   ___  \n /'___) \n| (__   \n| ,__)  \n| |     \n(_)     \n        \n        \n",
    "g": "        \n        \n   __   \n /'_ `\\ \n( (_) | \n`\\__  | \n( )_) | \n \\___/' \n",
    "h": " _      \n( )     \n| |__   \n|  _ `\\ \n| | | | \n(_) (_) \n        \n        \n",
    "i": "    \n _  \n(_) \n| | \n| | \n(_) \n    \n    \n",
    "j": "        \n     _  \n    (_) \n    | | \n    | | \n _  | | \n( )_| | \n`\\___/' \n",
    "k": " _      \n( )     \n| |/')  \n| , <   \n| |\\`\\  \n(_) (_) \n        \n        \n",
    "l": " _    \n(_ )  \n | |  \n | |  \n | |  \n(___) \n      \n      \n",
    "m": "            \n            \n  ___ ___   \n/' _ ` _ `\\ \n| ( ) ( ) | \n(_) (_) (_) \n            \n            \n",
    "n": "        \n        \n  ___   \n/' _ `\\ \n| ( ) | \n(_) (_) \n        \n        \n",
    "o": "        \n        \n   _    \n /'_`\\  \n( (_) ) \n`\\___/' \n        \n        \n",
    "p": "        \n        \n _ _    \n( '_`\\  \n| (_) ) \n| ,__/' \n| |     \n(_)     \n",
    "q": "        \n        \n   _ _  \n /'_` ) \n( (_) | \n`\\__, | \n    | | \n    (_) \n",
    "r": "       \n       \n _ __  \n( '__) \n| |    \n(_)    \n       \n       \n",
    "s": "       \n       \n  ___  \n/',__) \n\\__, \\ \n(____/ \n       \n       \n",
    "t": " _    \n( )_  \n| ,_) \n| |   \n| |_  \n`\\__) \n      \n      \n",
    "u": "        \n        \n _   _  \n( ) ( ) \n| (_) | \n`\\___/' \n        \n        \n",
    "v": "        \n        \n _   _  \n( ) ( ) \n| \\_/ | \n`\\___/' \n        \n        \n",
    "w": "            \n            \n _   _   _  \n( ) ( ) ( ) \n| \\_/ \\_/ | \n`\\___x___/' \n            \n            \n",
    "x": "       \n       \n       \n(`\\/') \n >  <  \n(_/\\_) \n       \n       \n",
    "y": "        \n        \n _   _  \n( ) ( ) \n| (_) | \n`\\__, | \n( )_| | \n`\\___/' \n",
    "z": "       \n       \n ____  \n(_  ,) \n /'/_  \n(____) \n       \n       \n",
    "{": "    _  \n  /' ) \n | ,/' \n<' |   \n | `\\  \n `\\__) \n       \n       \n",
    "|": "    \n _  \n( ) \n| | \n| | \n| | \n(_) \n    \n",
    "}": " _     \n( `\\   \n`\\  |  \n  | `> \n /' |  \n(__/'  \n       \n       \n",
    "~": "   _   _  \n /' \\/' ) \n(_/\\__/'  \n          \n          \n          \n          \n          \n"
}