{
    " ": "   \n   \n   \n   \n",
    "!": "|| \nL| \n   \n() \n   \n",
    "\"": "     \n[][] \n     \n     \n     \n",
    "#": "        \n_||_||_ \n || ||  \n-L|-L|- \n        \n",
    "$": " |L  \n/ _| \n\\_ \\ \n|__/ \n L|  \n",
    "&": "",
    "'": " _ \n// \n   \n   \n   \n",
    "(": "  _ \n // \n||  \n||  \n \\\\ \n",
    ")": "_   \n\\\\  \n || \n || \n//  \n",
    "*": ". , \n x  \n' ` \n    \n    \n",
    "+": "       \n _||_  \n|_  _| \n  L|   \n       \n",
    ",": "    \n    \n    \n()  \nV   \n",
    "-": "     \n     \n __  \n|__| \n     \n",
    ".": "    \n    \n    \n()  \n    \n",
    "/": "   _ \n  // \n //  \n//   \n     \n",
    "0": "  _   \n / \\  \n| 0 | \n \\_/  \n      \n",
    "1": " _  \n/o| \n || \n L| \n    \n",
    "2": " __  \n[o ) \n /(  \n/__| \n     \n",
    "3": " ___ \n|_ / \n__)\\ \n\\__/ \n     \n",
    "4": "   .  \n  /|  \n /o|  \nL___| \n      \n",
    "5": " __  \n| _/ \n\\_ \\ \n|__/ \n     \n",
    "6": "  _  \n //  \n/o \\ \n\\__/ \n     \n",
    "7": " ____ \n|__ / \n  //  \n //   \n      \n",
    "8": " __  \n(o ) \n/o \\ \n\\__/ \n     \n",
    "9": " __  \n/o \\ \n\\_ / \n //  \n     \n",
    ":": "   \n   \n() \n() \n   \n",
    ";": "   \n   \n() \n() \nV  \n",
    "<": "  _ \n // \n<<  \n \\\\ \n    \n",
    "=": "",
    ">": "_   \n\\\\  \n >> \n//  \n    \n",
    "?": " __  \n|o ) \n //  \n     \n ()  \n",
    "@": "  __  \n /_ \\ \n((o_/ \n \\__7 \n      \n",
    "A": "  _   \n / \\  \n| o | \n|_n_| \n      \n",
    "B": " ___  \n| o ) \n| o \\ \n|___/ \n      \n",
    "C": "  __  \n / _| \n( (_  \n \\__| \n      \n",
    "D": " __   \n|  \\  \n| o ) \n|__/  \n      \n",
    "E": " ___  \n| __| \n| _|  \n|___| \n      \n",
    "F": " ___  \n| __| \n| _|  \n|_|   \n      \n",
    "G": "  __  \n / _| \n( |_n \n \\__/ \n      \n",
    "H": " _ _  \n| U | \n|   | \n|_n_| \n      \n",
    "I": " _  \n| | \n| | \n|_| \n    \n",
    "J": "   _  \n  | | \nn_| | \n\\__/  \n      \n",
    "K": " _  _ \n| |// \n|  (  \n|_|\\\\ \n      \n",
    "L": " _    \n| |   \n| |_  \n|___| \n      \n",
    "M": " _   _  \n| \\_/ | \n| \\_/ | \n|_| |_| \n        \n",
    "N": " _  _  \n| \\| | \n| \\\\ | \n|_|\\_| \n       \n",
    "O": "  _   \n / \\  \n( o ) \n \\_/  \n      \n",
    "P": " ___  \n| o \\ \n|  _/ \n|_|   \n      \n",
    "Q": "  _   \n / \\  \n( o ) \n \\_,7 \n      \n",
    "R": " ___  \n| o \\ \n|   / \n|_|\\\\ \n      \n",
    "S": " __  \n/ _| \n\\_ \\ \n|__/ \n     \n",
    "T": " ___  \n|_ _| \n | |  \n |_|  \n      \n",
    "U": " _ _  \n| | | \n| U | \n|___| \n      \n",
    "V": " _ _  \n| | | \n| V | \n \\_/  \n      \n",
    "W": " _ _ _  \n| | | | \n| V V | \n \\_n_/  \n        \n",
    "X": "__ __ \n\\ V / \n ) (  \n/_n_\\ \n      \n",
    "Y": "__ __ \n\\ V / \n \\ /  \n |_|  \n      \n",
    "Z": " ___  \n|_ /  \n /(_  \n/___| \n      \n",
    "[": " __  \n| _| \n| |  \n| |  \n|__| \n",
    "\\": "_    \n\\\\   \n \\\\  \n  \\\\ \n     \n",
    "]": " __  \n|_ | \n | | \n | | \n|__| \n",
    "^": " _  \n/n\\ \n    \n    \n    \n",
    "_": "      \n      \n      \n ___  \n|___| \n",
    "`": "_  \n\\\\ \n   \n   \n   \n",
    "a": "     \n _   \n/o\\  \n\\_,] \n     \n",
    "b": "    \n||  \n|o\\ \n|_/ \n    \n",
    "c": "   \n _ \n// \n\\\\ \n   \n",
    "d": "    \n || \n/o| \n\\_| \n    \n",
    "e": "    \n _  \n/o\\ \n\\(  \n    \n",
    "f": " __  \n/ _| \n| ]  \nL|   \n     \n",
    "g": "    \n _  \n/o\\ \n\\_/ \n _) \n",
    "h": "    \n||  \n| \\ \nLn| \n    \n",
    "i": "   \n() \n|| \nL| \n   \n",
    "j": "   \n() \n|| \n|| \n// \n",
    "k": "    \n||  \n|/7 \nL|\\ \n    \n",
    "l": "   \n|| \n|| \nL| \n   \n",
    "m": "       \n  _ _  \n|/ \\ \\ \nL_n_n| \n       \n",
    "n": "     \n  _  \n|/ \\ \nL_n| \n     \n",
    "o": "    \n _  \n/o\\ \n\\_/ \n    \n",
    "p": "    \n _  \n/o\\ \n|_/ \nL|  \n",
    "q": "    \n _  \n/o\\ \n\\_| \n L| \n",
    "r": "    \n _  \n/_| \nL|  \n    \n",
    "s": "    \n _  \n(c' \n\\_) \n    \n",
    "t": "    \n||  \n| ] \nL|  \n    \n",
    "u": "    \n    \n|U| \n\\_/ \n    \n",
    "v": "    \n    \n\\V7 \n V  \n    \n",
    "w": "     \n     \n\\VV7 \n VV  \n     \n",
    "x": "    \n    \n\\V7 \n/n\\ \n    \n",
    "y": "     \n__   \n\\ V7 \n )/  \n//   \n",
    "z": "      \n __   \n|_ /  \n /__| \n      \n",
    "{": "  _ \n // \n/|  \n\\|  \n \\\\ \n",
    "|": " _  \n| | \n| | \n| | \n|_| \n",
    "}": "_   \n\\\\  \n |\\ \n |/ \n//  \n",
    "~": " _   \n//V7 \n     \n     \n     \n"
}