{
    " ": "",
    "&": "",
    "*": "* \n  \n  \n  \n  \n  \n  \n  \n  \n  \n  \n  \n",
    "-": "- \n  \n  \n  \n  \n  \n  \n  \n  \n  \n  \n  \n",
    ".": "        \n        \n        \n        \n        \n        \n        \n        \n  ___   \n |   |  \n |___|  \n        \n",
    "0": "0 \n  \n  \n  \n  \n  \n  \n  \n  \n  \n  \n  \n",
    "9": "9 \n  \n  \n  \n  \n  \n  \n  \n  \n  \n  \n  \n",
    "=": "",
    "A": "                   \n    _____          \n  /      |_        \n /         \\       \n|     /\\    \\      \n|    |  |    \\     \n|     \\/      \\    \n|\\      /\\     \\   \n| \\_____\\ \\_____\\  \n| |     | |     |  \n \\|_____|\\|_____|  \n                   \n",
    "B": "                  \n______  ______    \n\\     \\|\\     \\   \n |     |\\|     |  \n |     |/____ /   \n |     |\\     \\   \n |     | |     |  \n |     | |     |  \n/_____/|/_____/|  \n|    |||     | |  \n|____|/|_____|/   \n                  \n",
    "C": "                  \n        _____     \n   _____\\    \\_   \n  /     /|     |  \n /     / /____/|  \n|     | |____|/   \n|     |  _____    \n|\\     \\|\\    \\   \n| \\_____\\|    |   \n| |     /____/|   \n \\|_____|    ||   \n        |____|/   \n",
    "D": "                  \n ____________     \n \\           \\    \n  \\           \\   \n   |    /\\     |  \n   |   |  |    |  \n   |    \\/     |  \n  /           /|  \n /___________/ |  \n|           | /   \n|___________|/    \n                  \n",
    "E": "        _____    \n   _____\\    \\   \n  /    / |    |  \n /    /  /___/|  \n|    |__ |___|/  \n|       \\        \n|     __/ __     \n|\\    \\  /  \\    \n| \\____\\/    |   \n| |    |____/|   \n \\|____|   | |   \n       |___|/    \n",
    "F": "       _____     \n ____  \\    \\    \n \\   \\ /____/|   \n  |  |/_____|/   \n  |  |    ___    \n  |   \\__/   \\   \n /      /\\___/|  \n/      /| | | |  \n|_____| /\\|_|/   \n|     |/         \n|_____|          \n                 \n",
    "G": "                      \n        _____         \n   _____\\    \\_       \n  /     /|     |      \n /     / /____/|      \n|     | |_____|/      \n|     | |_________    \n|\\     \\|\\        \\   \n| \\_____\\|    |\\__/|  \n| |     /____/| | ||  \n \\|_____|     |\\|_|/  \n        |____/        \n",
    "H": "                         \n       __     __         \n      /  \\   /  \\        \n     /   /| |\\   \\       \n    /   //   \\\\   \\      \n   /    \\_____/    \\     \n  /    /\\_____/\\    \\    \n /    //\\_____/\\\\    \\   \n/____/ |       | \\____\\  \n|    | |       | |    |  \n|____|/         \\|____|  \n                         \n",
    "I": "                  \n  ____________    \n /            \\   \n|\\___/\\  \\\\___/|  \n \\|____\\  \\___|/  \n       |  |       \n  __  /   / __    \n /  \\/   /_/  |   \n|____________/|   \n|           | /   \n|___________|/    \n                  \n",
    "J": "                     \n          _____      \n         |\\    \\_    \n         \\ \\     \\   \n          \\|      |  \n           |      |  \n   ______  |      |  \n  /     / /      /|  \n |      |/______/ |  \n |\\_____\\      | /   \n | |     |_____|/    \n  \\|_____|           \n",
    "K": "                     \n ______   _______    \n|\\     \\  \\      \\   \n \\\\     \\  |     /|  \n  \\|     |/     //   \n   |     |_____//    \n   |     |\\     \\    \n  /     /|\\|     |   \n /_____/ |/_____/|   \n|     | / |    | |   \n|_____|/  |____|/    \n                     \n",
    "L": "                    \n _____              \n|\\    \\             \n \\\\    \\            \n  \\\\    \\           \n   \\|    | ______   \n    |    |/      \\  \n    /            |  \n   /_____/\\_____/|  \n  |      | |    ||  \n  |______|/|____|/  \n                    \n",
    "M": "                             \n        ___________          \n       /           \\         \n      /    _   _    \\        \n     /    //   \\\\    \\       \n    /    //     \\\\    \\      \n   /     \\\\_____//     \\     \n  /       \\ ___ /       \\    \n /________/|   |\\________\\   \n|        | |   | |        |  \n|________|/     \\|________|  \n                             \n",
    "N": "                     \n _____    _____      \n|\\    \\   \\    \\     \n \\\\    \\   |    |    \n  \\\\    \\  |    |    \n   \\|    \\ |    |    \n    |     \\|    |    \n   /     /\\      \\   \n  /_____/ /______/|  \n |      | |     | |  \n |______|/|_____|/   \n                     \n",
    "O": "                  \n       ____       \n   ____\\_  \\__    \n  /     /     \\   \n /     /\\      |  \n|     |  |     |  \n|     |  |     |  \n|     | /     /|  \n|\\     \\_____/ |  \n| \\_____\\   | /   \n \\ |    |___|/    \n  \\|____|         \n",
    "P": "        ______    \n  _____|\\     \\   \n /     / |     |  \n|      |/     /|  \n|      |\\____/ |  \n|\\     \\    | /   \n| \\     \\___|/    \n|  \\     \\        \n \\  \\_____\\       \n  \\ |     |       \n   \\|_____|       \n                  \n",
    "Q": "      ______       \n   ___\\__   \\_     \n  /     /     \\    \n /     /\\     |    \n|     |  |    |    \n|     | /     |    \n|     |/     /|    \n|\\     \\_   /_|_   \n| \\_____\\\\______\\  \n| |     |       |  \n \\|_____|_______|  \n                   \n",
    "R": "                   \n___________        \n\\          \\       \n \\    /\\    \\      \n  |   \\_\\    |     \n  |      ___/      \n  |      \\  ____   \n /     /\\ \\/    \\  \n/_____/ |\\______|  \n|     | | |     |  \n|_____|/ \\|_____|  \n                   \n",
    "S": "                     \n            _____    \n       _____\\    \\   \n      /    / \\    |  \n     |    |  /___/|  \n  ____\\    \\ |   ||  \n /    /\\    \\|___|/  \n|    |/ \\    \\       \n|\\____\\ /____/|      \n| |   ||    | |      \n \\|___||____|/       \n                     \n",
    "T": "                          \n  ________    ________    \n /        \\  /        \\   \n|\\         \\/         /|  \n| \\            /\\____/ |  \n|  \\______/\\   \\     | |  \n \\ |      | \\   \\____|/   \n  \\|______|  \\   \\        \n           \\  \\___\\       \n            \\ |   |       \n             \\|___|       \n                          \n",
    "U": "                    \n______   _____      \n\\     \\  \\    \\     \n \\    |  |    |     \n  |   |  |    |     \n  |    \\_/   /|     \n  |\\         \\|     \n  | \\         \\__   \n   \\ \\_____/\\    \\  \n    \\ |    |/___/|  \n     \\|____|   | |  \n           |___|/   \n",
    "V": "                    \n_______    ______   \n\\      |  |      |  \n |     /  /     /|  \n |\\    \\  \\    |/   \n \\ \\    \\ |    |    \n  \\|     \\|    |    \n   |\\         /|    \n   | \\_______/ |    \n    \\ |     | /     \n     \\|_____|/      \n                    \n",
    "W": "                           \n   _______     _______     \n  /      /|   |\\      \\    \n /      / |   | \\      \\   \n|      /  |___|  \\      |  \n|      |  |   |  |      |  \n|       \\ \\   / /       |  \n|      |\\\\/   \\//|      |  \n|\\_____\\|\\_____/|/_____/|  \n| |     | |   | |     | |  \n \\|_____|\\|___|/|_____|/   \n                           \n",
    "X": "                   \n_____       _____  \n\\    \\     /    /  \n \\    |   |    /   \n  \\    \\ /    /    \n   \\    |    /     \n   /    |    \\     \n  /    /|\\    \\    \n |____|/ \\|____|   \n |    |   |    |   \n |____|   |____|   \n                   \n",
    "Y": "                  \n ______   _____   \n|\\     \\ |     |  \n\\ \\     \\|     |  \n \\ \\           |  \n  \\ \\____      |  \n   \\|___/     /|  \n       /     / |  \n      /_____/  /  \n      |     | /   \n      |_____|/    \n                  \n",
    "Z": "                    \n  _____  ______     \n /    / /     /|    \n|     |/     / |    \n|\\____\\\\    / /     \n \\|___|/   / /      \n    /     /_/____   \n   /     /\\      |  \n  /_____/ /_____/|  \n  |    |/|     | |  \n  |____| |_____|/   \n                    \n",
    "a": "                   \n    _____          \n  /      |_        \n /         \\       \n|     /\\    \\      \n|    |  |    \\     \n|     \\/      \\    \n|\\      /\\     \\   \n| \\_____\\ \\_____\\  \n| |     | |     |  \n \\|_____|\\|_____|  \n                   \n",
    "b": "                  \n______  ______    \n\\     \\|\\     \\   \n |     |\\|     |  \n |     |/____ /   \n |     |\\     \\   \n |     | |     |  \n |     | |     |  \n/_____/|/_____/|  \n|    |||     | |  \n|____|/|_____|/   \n                  \n",
    "c": "                  \n        _____     \n   _____\\    \\_   \n  /     /|     |  \n /     / /____/|  \n|     | |____|/   \n|     |  _____    \n|\\     \\|\\    \\   \n| \\_____\\|    |   \n| |     /____/|   \n \\|_____|    ||   \n        |____|/   \n",
    "d": "                  \n ____________     \n \\           \\    \n  \\           \\   \n   |    /\\     |  \n   |   |  |    |  \n   |    \\/     |  \n  /           /|  \n /___________/ |  \n|           | /   \n|___________|/    \n                  \n",
    "e": "        _____    \n   _____\\    \\   \n  /    / |    |  \n /    /  /___/|  \n|    |__ |___|/  \n|       \\        \n|     __/ __     \n|\\    \\  /  \\    \n| \\____\\/    |   \n| |    |____/|   \n \\|____|   | |   \n       |___|/    \n",
    "f": "       _____     \n ____  \\    \\    \n \\   \\ /____/|   \n  |  |/_____|/   \n  |  |    ___    \n  |   \\__/   \\   \n /      /\\___/|  \n/      /| | | |  \n|_____| /\\|_|/   \n|     |/         \n|_____|          \n                 \n",
    "g": "                      \n        _____         \n   _____\\    \\_       \n  /     /|     |      \n /     / /____/|      \n|     | |_____|/      \n|     | |_________    \n|\\     \\|\\        \\   \n| \\_____\\|    |\\__/|  \n| |     /____/| | ||  \n \\|_____|     |\\|_|/  \n        |____/        \n",
    "h": "                         \n       __     __         \n      /  \\   /  \\        \n     /   /| |\\   \\       \n    /   //   \\\\   \\      \n   /    \\_____/    \\     \n  /    /\\_____/\\    \\    \n /    //\\_____/\\\\    \\   \n/____/ |       | \\____\\  \n|    | |       | |    |  \n|____|/         \\|____|  \n                         \n",
    "i": "                  \n  ____________    \n /            \\   \n|\\___/\\  \\\\___/|  \n \\|____\\  \\___|/  \n       |  |       \n  __  /   / __    \n /  \\/   /_/  |   \n|____________/|   \n|           | /   \n|___________|/    \n                  \n",
    "j": "                     \n          _____      \n         |\\    \\_    \n         \\ \\     \\   \n          \\|      |  \n           |      |  \n   ______  |      |  \n  /     / /      /|  \n |      |/______/ |  \n |\\_____\\      | /   \n | |     |_____|/    \n  \\|_____|           \n",
    "k": "                     \n ______   _______    \n|\\     \\  \\      \\   \n \\\\     \\  |     /|  \n  \\|     |/     //   \n   |     |_____//    \n   |     |\\     \\    \n  /     /|\\|     |   \n /_____/ |/_____/|   \n|     | / |    | |   \n|_____|/  |____|/    \n                     \n",
    "l": "                    \n _____              \n|\\    \\             \n \\\\    \\            \n  \\\\    \\           \n   \\|    | ______   \n    |    |/      \\  \n    /            |  \n   /_____/\\_____/|  \n  |      | |    ||  \n  |______|/|____|/  \n                    \n",
    "m": "                             \n        ___________          \n       /           \\         \n      /    _   _    \\        \n     /    //   \\\\    \\       \n    /    //     \\\\    \\      \n   /     \\\\_____//     \\     \n  /       \\ ___ /       \\    \n /________/|   |\\________\\   \n|        | |   | |        |  \n|________|/     \\|________|  \n                             \n",
    "n": "                     \n _____    _____      \n|\\    \\   \\    \\     \n \\\\    \\   |    |    \n  \\\\    \\  |    |    \n   \\|    \\ |    |    \n    |     \\|    |    \n   /     /\\      \\   \n  /_____/ /______/|  \n |      | |     | |  \n |______|/|_____|/   \n                     \n",
    "o": "                  \n       ____       \n   ____\\_  \\__    \n  /     /     \\   \n /     /\\      |  \n|     |  |     |  \n|     |  |     |  \n|     | /     /|  \n|\\     \\_____/ |  \n| \\_____\\   | /   \n \\ |    |___|/    \n  \\|____|         \n",
    "p": "        ______    \n  _____|\\     \\   \n /     / |     |  \n|      |/     /|  \n|      |\\____/ |  \n|\\     \\    | /   \n| \\     \\___|/    \n|  \\     \\        \n \\  \\_____\\       \n  \\ |     |       \n   \\|_____|       \n                  \n",
    "q": "      ______       \n   ___\\__   \\_     \n  /     /     \\    \n /     /\\     |    \n|     |  |    |    \n|     | /     |    \n|     |/     /|    \n|\\     \\_   /_|_   \n| \\_____\\\\______\\  \n| |     |       |  \n \\|_____|_______|  \n                   \n",
    "r": "                   \n___________        \n\\          \\       \n \\    /\\    \\      \n  |   \\_\\    |     \n  |      ___/      \n  |      \\  ____   \n /     /\\ \\/    \\  \n/_____/ |\\______|  \n|     | | |     |  \n|_____|/ \\|_____|  \n                   \n",
    "s": "                     \n            _____    \n       _____\\    \\   \n      /    / \\    |  \n     |    |  /___/|  \n  ____\\    \\ |   ||  \n /    /\\    \\|___|/  \n|    |/ \\    \\       \n|\\____\\ /____/|      \n| |   ||    | |      \n \\|___||____|/       \n                     \n",
    "t": "                          \n  ________    ________    \n /        \\  /        \\   \n|\\         \\/         /|  \n| \\            /\\____/ |  \n|  \\______/\\   \\     | |  \n \\ |      | \\   \\____|/   \n  \\|______|  \\   \\        \n           \\  \\___\\       \n            \\ |   |       \n             \\|___|       \n                          \n",
    "u": "                    \n______   _____      \n\\     \\  \\    \\     \n \\    |  |    |     \n  |   |  |    |     \n  |    \\_/   /|     \n  |\\         \\|     \n  | \\         \\__   \n   \\ \\_____/\\    \\  \n    \\ |    |/___/|  \n     \\|____|   | |  \n           |___|/   \n",
    "v": "                    \n_______    ______   \n\\      |  |      |  \n |     /  /     /|  \n |\\    \\  \\    |/   \n \\ \\    \\ |    |    \n  \\|     \\|    |    \n   |\\         /|    \n   | \\_______/ |    \n    \\ |     | /     \n     \\|_____|/      \n                    \n",
    "w": "                           \n   _______     _______     \n  /      /|   |\\      \\    \n /      / |   | \\      \\   \n|      /  |___|  \\      |  \n|      |  |   |  |      |  \n|       \\ \\   / /       |  \n|      |\\\\/   \\//|      |  \n|\\_____\\|\\_____/|/_____/|  \n| |     | |   | |     | |  \n \\|_____|\\|___|/|_____|/   \n                           \n",
    "x": "                   \n_____       _____  \n\\    \\     /    /  \n \\    |   |    /   \n  \\    \\ /    /    \n   \\    |    /     \n   /    |    \\     \n  /    /|\\    \\    \n |____|/ \\|____|   \n |    |   |    |   \n |____|   |____|   \n                   \n",
    "y": "                  \n ______   _____   \n|\\     \\ |     |  \n\\ \\     \\|     |  \n \\ \\           |  \n  \\ \\____      |  \n   \\|___/     /|  \n       /     / |  \n      /_____/  /  \n      |     | /   \n      |_____|/    \n                  \n",
    "z": "                    \n  _____  ______     \n /    / /     /|    \n|     |/     / |    \n|\\____\\\\    / /     \n \\|___|/   / /      \n    /     /_/____   \n   /     /\\      |  \n  /_____/ /_____/|  \n  |    |/|     | |  \n  |____| |_____|/   \n                    \n"
}